{
 "data": [
  {
    "comment": "河南 郑州 联通",
    "ip": "srv.jaxlewis.top",
    "port": 11451,
    "flag": "cn"
  },
  {
    "comment": "浙江 嘉兴 电信",
    "ip": "yordon.cn",
    "port": 11451,
    "flag": "cn"
  },
  {
    "comment": "广东 深圳 电信",
    "ip": "aya0.top",
    "port": 11451,
    "flag": "cn"
  },
  {
    "comment": "广东 深圳 电信",
    "ip": "177040122.xyz",
    "port": 11451,
    "flag": "cn"
  },
  {
    "comment": "广东 广州 腾讯云",
    "ip": "1.12.75.193",
    "port": 11451,
    "flag": "cn"
  },
  {
    "comment": "上海 腾讯云",
    "ip": "42.192.8.201",
    "port": 11451,
    "flag": "cn"
  },
  {
    "comment": "四川 眉山 联通",
    "ip": "112.192.20.196",
    "port": 11451,
    "flag": "cn"
  },
  {
    "comment": "北京 华为云",
    "ip": "120.46.181.251",
    "port": 11451,
    "flag": "cn"
  },
  {
    "comment": "台湾 新北 中華電信",
    "ip": "122.116.141.58",
    "port": 11451,
    "flag": "tw"
  },
  {
    "comment": "美国",
    "ip": "joinsg.net",
    "port": 11453,
    "flag": "us"
  }
 ]
}
